{
    "fluentMethods": true,
    "relationships": [],
    "fields": [
        {
            "fieldName": "userId",
            "fieldType": "Integer",
            "fieldValidateRules": [
                "required"
            ]
        },
        {
            "fieldName": "description",
            "fieldType": "String",
            "fieldValidateRules": [
                "required",
                "maxlength"
            ],
            "fieldValidateRulesMaxlength": 100
        },
        {
            "fieldName": "type",
            "fieldType": "Integer",
            "fieldValidateRules": [
                "required"
            ]
        },
        {
            "fieldName": "isRead",
            "fieldType": "Boolean"
        },
        {
            "fieldName": "link",
            "fieldType": "String"
        },
        {
            "fieldName": "createdDate",
            "fieldType": "ZonedDateTime"
        }
    ],
    "changelogDate": "20180509122112",
    "entityTableName": "notification",
    "dto": "mapstruct",
    "pagination": "no",
    "service": "serviceImpl",
    "jpaMetamodelFiltering": false
}