{
    "fluentMethods": true,
    "relationships": [],
    "fields": [
        {
            "fieldName": "number",
            "fieldType": "String",
            "fieldValidateRules": [
                "required"
            ]
        },
        {
            "fieldName": "type",
            "fieldType": "PhoneType",
            "fieldValues": "HOME,CELL,OFFICE,OTHER"
        }
    ],
    "changelogDate": "20180419075316",
    "entityTableName": "phone",
    "dto": "mapstruct",
    "pagination": "no",
    "service": "serviceImpl",
    "jpaMetamodelFiltering": false
}